feature_toggle_manager/__init__.py
feature_toggle_manager/admin.py
feature_toggle_manager/apps.py
feature_toggle_manager/consumers.py
feature_toggle_manager/models.py
feature_toggle_manager/routing.py
feature_toggle_manager/serializers.py
feature_toggle_manager/signals.py
feature_toggle_manager/tests.py
feature_toggle_manager/urls.py
feature_toggle_manager/views.py
feature_toggle_manager/migrations/__init__.py
feature_toggle_manager-0.0.3.dist-info/LICENSE
feature_toggle_manager-0.0.3.dist-info/METADATA
feature_toggle_manager-0.0.3.dist-info/WHEEL
feature_toggle_manager-0.0.3.dist-info/top_level.txt
feature_toggle_manager-0.0.3.dist-info/RECORD
