Metadata-Version: 2.1
Name: feature-toggle-manager
Version: 0.0.3
Summary: A small feature_toggle_manager app for django
Author-email: Alejandro <agarrido@izertis.com>
Classifier: Programming Language :: Python :: 3
Classifier: License :: OSI Approved :: MIT License
Classifier: Operating System :: OS Independent
Requires-Python: >=3.7
License-File: LICENSE
Requires-Dist: Django (==4.1.3)
Requires-Dist: djangorestframework (==3.14.0)
Requires-Dist: drf-yasg (==1.21.4)
Requires-Dist: django-waffle (==3.0.0)
Requires-Dist: channels (==4.0.0)
Requires-Dist: daphne (==4.0.0)
Requires-Dist: websocket-client (==1.4.2)
Requires-Dist: asgiref (==3.6.0)
